gpt_engine/__init__.py
gpt_engine/config.py
gpt_engine/gpt_engine.py
gptEngine-0.0.2.dist-info/LICENSE
gptEngine-0.0.2.dist-info/METADATA
gptEngine-0.0.2.dist-info/WHEEL
gptEngine-0.0.2.dist-info/top_level.txt
gptEngine-0.0.2.dist-info/RECORD
