Metadata-Version: 2.1
Name: gptEngine
Version: 0.0.2
Summary: OPENAI tool that runs your prompts over a document
Author-email: Bhanu Suraj Malla <bsmalla@asu.edu>
Project-URL: Homepage, https://github.com/mbsuraj/gptEngine
Project-URL: Bug Tracker, https://github.com/mbsuraj/gptEngine/issues
Classifier: Programming Language :: Python :: 3
Classifier: License :: OSI Approved :: MIT License
Classifier: Operating System :: OS Independent
Requires-Python: >=3.7
License-File: LICENSE
